yahoofinanceasyncio/__init__.py
yahoofinanceasyncio/scapeasync.py
yahoofinanceasyncio/scrapeone.py
yahoofinanceasyncio/yfasync.py
yahoofinanceasyncio/yfin.py
yahoofinanceasyncio/yfmulti.py
yahoofinanceasyncio-0.0.3.dist-info/LICENSE
yahoofinanceasyncio-0.0.3.dist-info/METADATA
yahoofinanceasyncio-0.0.3.dist-info/WHEEL
yahoofinanceasyncio-0.0.3.dist-info/entry_points.txt
yahoofinanceasyncio-0.0.3.dist-info/top_level.txt
yahoofinanceasyncio-0.0.3.dist-info/RECORD
