Metadata-Version: 2.1
Name: yahoofinanceasyncio
Version: 0.0.3
Summary: Yahoo prices
Home-page: https://github.com/microprediction/yahoofinanceasyncio
Author: microprediction
Author-email: peter.cotton@microprediction.com
License: MIT
Classifier: License :: OSI Approved :: MIT License
Classifier: Programming Language :: Python :: 3
Classifier: Programming Language :: Python :: 3.8
Classifier: Programming Language :: Python :: 3.8
License-File: LICENSE
Requires-Dist: numpy
